docs/trajectory_plot.py
kino/__init__.py
kino/animal.py
kino/locomotion.py
kino/math.py
kino/progress.py
kino/steps.py
kino/animate/__init__.py
kino/animate/base.py
kino/animate/complete.py
kino/draw/__init__.py
kino/draw/animal.py
kino/draw/colors.py
kino/draw/gliphs.py
kino/draw/kinematics.py
kino/draw/locomotion.py
kino/geometry/__init__.py
kino/geometry/coordinates.py
kino/geometry/interpolation.py
kino/geometry/point.py
kino/geometry/projections.py
kino/geometry/trajectory.py
kino/geometry/vector.py
kino/geometry/vectors_utils.py
scripts/animal.py
scripts/animal_trajectory.py
scripts/animal_trajectory_to_ego.py
scripts/animation_complete.py
scripts/animation_pose.py
scripts/animation_scalar.py
scripts/animation_vector.py
scripts/draw_animal_at_frame.py
scripts/plot_steps.py
tests/__init__.py
tests/test_animations.py
tests/test_coordinates.py
tests/test_maths.py
tests/test_trajectory.py
tests/test_vector.py
tests/test_vector_utils.py
kino-0.0.1.dist-info/LICENSE
kino-0.0.1.dist-info/METADATA
kino-0.0.1.dist-info/WHEEL
kino-0.0.1.dist-info/entry_points.txt
kino-0.0.1.dist-info/top_level.txt
kino-0.0.1.dist-info/RECORD
