Metadata-Version: 2.1
Name: kino
Version: 0.0.1
Summary: Locomotion kinematics analysis
Home-page: UNKNOWN
Author: Federico Claudi
License: UNKNOWN
Platform: UNKNOWN
Requires-Python: >=3.6
Requires-Dist: numpy
Requires-Dist: matplotlib
Requires-Dist: rich
Requires-Dist: myterial
Requires-Dist: sklearn
Requires-Dist: celluloid
Requires-Dist: pyinspect
Requires-Dist: loguru
